[
  {
    "version": "main",
    "url": "https://eclipse-score.github.io/logging/main/"
  },
  {
    "version": "pr-33",
    "url": "https://eclipse-score.github.io/logging/pr-33/"
  },
  {
    "version": "pr-38",
    "url": "https://eclipse-score.github.io/logging/pr-38/"
  },
  {
    "version": "pr-40",
    "url": "https://eclipse-score.github.io/logging/pr-40/"
  },
  {
    "version": "pr-44",
    "url": "https://eclipse-score.github.io/logging/pr-44/"
  },
  {
    "version": "pr-46",
    "url": "https://eclipse-score.github.io/logging/pr-46/"
  }
]
